USSCameraTools/__init__.py
USSCameraTools/core.py
USSCameraTools-0.1.2.dist-info/METADATA
USSCameraTools-0.1.2.dist-info/WHEEL
USSCameraTools-0.1.2.dist-info/top_level.txt
USSCameraTools-0.1.2.dist-info/RECORD
