Metadata-Version: 2.1
Name: USSCameraTools
Version: 0.1.2
Summary: USSCamera: Python package for interacting with GigE cameras using the Harvesters library
Home-page: https://github.com/USSVision/USSCommonTools/tree/main/Packages/USSCameraTools
Author: USS Vision
Author-email: bhelfer@ussvision.com
License: MIT
Platform: UNKNOWN
Classifier: Development Status :: 4 - Beta
Classifier: License :: OSI Approved :: MIT License
Classifier: Operating System :: POSIX :: Linux
Classifier: Operating System :: Microsoft :: Windows :: Windows 10
Classifier: Programming Language :: Python :: 3.7
Classifier: Programming Language :: Python :: 3.8
Classifier: Programming Language :: Python :: 3.9
Classifier: Programming Language :: Python :: 3.10
Requires-Dist: harvesters
Requires-Dist: opencv-python
Requires-Dist: wheel
